odoo8_addon_hr_employee_phone_extension-8.0.1.0.0.99.dev8-py2.7-nspkg.pth
odoo8_addon_hr_employee_phone_extension-8.0.1.0.0.99.dev8.dist-info/DESCRIPTION.rst
odoo8_addon_hr_employee_phone_extension-8.0.1.0.0.99.dev8.dist-info/METADATA
odoo8_addon_hr_employee_phone_extension-8.0.1.0.0.99.dev8.dist-info/RECORD
odoo8_addon_hr_employee_phone_extension-8.0.1.0.0.99.dev8.dist-info/WHEEL
odoo8_addon_hr_employee_phone_extension-8.0.1.0.0.99.dev8.dist-info/metadata.json
odoo8_addon_hr_employee_phone_extension-8.0.1.0.0.99.dev8.dist-info/namespace_packages.txt
odoo8_addon_hr_employee_phone_extension-8.0.1.0.0.99.dev8.dist-info/top_level.txt
odoo_addons/hr_employee_phone_extension/README.rst
odoo_addons/hr_employee_phone_extension/__init__.py
odoo_addons/hr_employee_phone_extension/__openerp__.py
odoo_addons/hr_employee_phone_extension/i18n/ar.po
odoo_addons/hr_employee_phone_extension/i18n/de.po
odoo_addons/hr_employee_phone_extension/i18n/es.po
odoo_addons/hr_employee_phone_extension/i18n/fi.po
odoo_addons/hr_employee_phone_extension/i18n/fr.po
odoo_addons/hr_employee_phone_extension/i18n/hr_employee_phone_extension.pot
odoo_addons/hr_employee_phone_extension/i18n/it.po
odoo_addons/hr_employee_phone_extension/i18n/nl.po
odoo_addons/hr_employee_phone_extension/i18n/nl_NL.po
odoo_addons/hr_employee_phone_extension/i18n/pt_BR.po
odoo_addons/hr_employee_phone_extension/i18n/ro.po
odoo_addons/hr_employee_phone_extension/i18n/sl.po
odoo_addons/hr_employee_phone_extension/models/__init__.py
odoo_addons/hr_employee_phone_extension/models/hr_employee.py
odoo_addons/hr_employee_phone_extension/static/description/icon.png
odoo_addons/hr_employee_phone_extension/views/hr_employee_view.xml
